{
  "lat": 50.75,
  "lon": 5.91,
  "fetched_at": "2026-02-21T06:33:03.901261",
  "observation_count": 111,
  "observations": [
    {
      "id": "wn_386042949",
      "species": "Rode Wouw",
      "scientific_name": "Milvus milvus",
      "lat": 50.762081146240234,
      "lon": 5.927444458007812,
      "observed_on": "2026-02-14",
      "time": "15:15",
      "location_name": "Geuldal - Zuid van Epen",
      "source": "waarneming_nl",
      "category": "bird",
      "rarity": 2,
      "rarity_label": "vrij_algemeen",
      "photo_url": "",
      "permalink": "https://waarneming.nl/observation/386042949/",
      "count": 1,
      "distance_km": 1.82
    },
    {
      "id": "wn_386016573",
      "species": "Das",
      "scientific_name": "Meles meles",
      "lat": 50.781861666666664,
      "lon": 5.973345,
      "observed_on": "2026-02-14",
      "time": "14:48",
      "location_name": "Harles e.o.",
      "source": "waarneming_nl",
      "category": "mammal",
      "rarity": 2,
      "rarity_label": "vrij_algemeen",
      "photo_url": "https://waarneming.nl/media/photo/144041488.jpg",
      "permalink": "https://waarneming.nl/observation/386016573/",
      "count": 1,
      "distance_km": 5.69
    },
    {
      "id": "wn_386012863",
      "species": "Das",
      "scientific_name": "Meles meles",
      "lat": 50.87064299036624,
      "lon": 5.943648576561714,
      "observed_on": "2026-02-14",
      "time": "11:04",
      "location_name": "Voerendaal - Kunderberg ",
      "source": "waarneming_nl",
      "category": "mammal",
      "rarity": 2,
      "rarity_label": "vrij_algemeen",
      "photo_url": "https://waarneming.nl/media/photo/144039515.jpg",
      "permalink": "https://waarneming.nl/observation/386012863/",
      "count": 1,
      "distance_km": 13.62
    },
    {
      "id": "wn_385989062",
      "species": "Europese Rode Eekhoorn",
      "scientific_name": "Sciurus vulgaris",
      "lat": 50.87141010240635,
      "lon": 5.988149642944336,
      "observed_on": "2026-02-14",
      "time": "10:21",
      "location_name": "Heerlen - Douveweien",
      "source": "waarneming_nl",
      "category": "mammal",
      "rarity": 2,
      "rarity_label": "vrij_algemeen",
      "photo_url": "",
      "permalink": "https://waarneming.nl/observation/385989062/",
      "count": 1,
      "distance_km": 14.57
    },
    {
      "id": "wn_386120371",
      "species": "Taigaboomkruiper",
      "scientific_name": "Certhia familiaris",
      "lat": 50.76654758219466,
      "lon": 5.963936805201229,
      "observed_on": "2026-02-15",
      "time": "12:59",
      "location_name": "Vaals - Kerperbos",
      "source": "waarneming_nl",
      "category": "bird",
      "rarity": 3,
      "rarity_label": "zeldzaam",
      "photo_url": "https://waarneming.nl/media/photo/144086065.jpg",
      "permalink": "https://waarneming.nl/observation/386120371/",
      "count": 1,
      "distance_km": 4.22
    },
    {
      "id": "wn_386071304",
      "species": "Middelste Bonte Specht",
      "scientific_name": "Dendrocoptes medius",
      "lat": 50.7664888,
      "lon": 5.964473600000019,
      "observed_on": "2026-02-15",
      "time": "12:09",
      "location_name": "Vaals - Kerperbos",
      "source": "waarneming_nl",
      "category": "bird",
      "rarity": 2,
      "rarity_label": "vrij_algemeen",
      "photo_url": "",
      "permalink": "https://waarneming.nl/observation/386071304/",
      "count": 1,
      "distance_km": 4.25
    },
    {
      "id": "wn_386069148",
      "species": "Europese Rode Eekhoorn",
      "scientific_name": "Sciurus vulgaris",
      "lat": 50.85265619778634,
      "lon": 5.839915849673616,
      "observed_on": "2026-02-15",
      "time": "11:50",
      "location_name": "Valkenburg - Biebosch",
      "source": "waarneming_nl",
      "category": "mammal",
      "rarity": 2,
      "rarity_label": "vrij_algemeen",
      "photo_url": "",
      "permalink": "https://waarneming.nl/observation/386069148/",
      "count": 1,
      "distance_km": 12.43
    },
    {
      "id": "wn_386086172",
      "species": "Wild Zwijn",
      "scientific_name": "Sus scrofa",
      "lat": 50.8524169921875,
      "lon": 5.829546971843305,
      "observed_on": "2026-02-15",
      "time": "14:28",
      "location_name": "Valkenburg - Sibbergrubbe",
      "source": "waarneming_nl",
      "category": "mammal",
      "rarity": 2,
      "rarity_label": "vrij_algemeen",
      "photo_url": "https://waarneming.nl/media/photo/144071437.jpg",
      "permalink": "https://waarneming.nl/observation/386086172/",
      "count": 1,
      "distance_km": 12.71
    },
    {
      "id": "wn_386188325",
      "species": "Rode Wouw",
      "scientific_name": "Milvus milvus",
      "lat": 50.830032641417766,
      "lon": 5.946103334442221,
      "observed_on": "2026-02-16",
      "time": "09:22",
      "location_name": "Gulpen-Wittem - Kromhagerweg e.o.",
      "source": "waarneming_nl",
      "category": "bird",
      "rarity": 2,
      "rarity_label": "vrij_algemeen",
      "photo_url": "",
      "permalink": "https://waarneming.nl/observation/386188325/",
      "count": 1,
      "distance_km": 9.25
    },
    {
      "id": "wn_386215669",
      "species": "Boommarter",
      "scientific_name": "Martes martes",
      "lat": 50.851409912109375,
      "lon": 5.833660527410661,
      "observed_on": "2026-02-17",
      "time": "16:44",
      "location_name": "Valkenburg - Sibbergrubbe",
      "source": "waarneming_nl",
      "category": "mammal",
      "rarity": 2,
      "rarity_label": "vrij_algemeen",
      "photo_url": "https://waarneming.nl/media/photo/144128924.jpg",
      "permalink": "https://waarneming.nl/observation/386215669/",
      "count": 1,
      "distance_km": 12.49
    },
    {
      "id": "wn_386253809",
      "species": "Rode Wouw",
      "scientific_name": "Milvus milvus",
      "lat": 50.77158583245345,
      "lon": 5.908775160839545,
      "observed_on": "2026-02-18",
      "time": "12:26",
      "location_name": "Epen",
      "source": "waarneming_nl",
      "category": "bird",
      "rarity": 2,
      "rarity_label": "vrij_algemeen",
      "photo_url": "",
      "permalink": "https://waarneming.nl/observation/386253809/",
      "count": 2,
      "distance_km": 2.4
    },
    {
      "id": "wn_386239387",
      "species": "Europese Bever",
      "scientific_name": "Castor fiber",
      "lat": 50.7904998,
      "lon": 5.9150926,
      "observed_on": "2026-02-18",
      "time": "08:33",
      "location_name": "Mechelen - H\u00f6fke e.o.",
      "source": "waarneming_nl",
      "category": "mammal",
      "rarity": 2,
      "rarity_label": "vrij_algemeen",
      "photo_url": "https://waarneming.nl/media/photo/144140150.jpg",
      "permalink": "https://waarneming.nl/observation/386239387/",
      "count": 1,
      "distance_km": 4.52
    },
    {
      "id": "wn_386262940",
      "species": "Rode Wouw",
      "scientific_name": "Milvus milvus",
      "lat": 50.78086332743668,
      "lon": 5.787445306777954,
      "observed_on": "2026-02-18",
      "time": "14:03",
      "location_name": "Mheer - Trichterweg e.o.",
      "source": "waarneming_nl",
      "category": "bird",
      "rarity": 2,
      "rarity_label": "vrij_algemeen",
      "photo_url": "https://waarneming.nl/media/photo/144150869.jpg",
      "permalink": "https://waarneming.nl/observation/386262940/",
      "count": 1,
      "distance_km": 9.28
    },
    {
      "id": "wn_386244395",
      "species": "Rode Wouw",
      "scientific_name": "Milvus milvus",
      "lat": 50.85650567192463,
      "lon": 5.9488445520401,
      "observed_on": "2026-02-18",
      "time": "09:45",
      "location_name": "Ubachsberg",
      "source": "waarneming_nl",
      "category": "bird",
      "rarity": 2,
      "rarity_label": "vrij_algemeen",
      "photo_url": "",
      "permalink": "https://waarneming.nl/observation/386244395/",
      "count": 4,
      "distance_km": 12.15
    },
    {
      "id": "wn_386286869",
      "species": "Das",
      "scientific_name": "Meles meles",
      "lat": 50.78867751450078,
      "lon": 5.729777812957764,
      "observed_on": "2026-02-18",
      "time": "06:30",
      "location_name": "Rijckholt - Voerenweg",
      "source": "waarneming_nl",
      "category": "mammal",
      "rarity": 2,
      "rarity_label": "vrij_algemeen",
      "photo_url": "",
      "permalink": "https://waarneming.nl/observation/386286869/",
      "count": 1,
      "distance_km": 13.38
    },
    {
      "id": "wn_386239153",
      "species": "Das",
      "scientific_name": "Meles meles",
      "lat": 50.8314999,
      "lon": 5.7560725,
      "observed_on": "2026-02-18",
      "time": "08:21",
      "location_name": "Cadier en Keer",
      "source": "waarneming_nl",
      "category": "mammal",
      "rarity": 2,
      "rarity_label": "vrij_algemeen",
      "photo_url": "https://waarneming.nl/media/photo/144140039.jpg",
      "permalink": "https://waarneming.nl/observation/386239153/",
      "count": 1,
      "distance_km": 14.11
    },
    {
      "id": "wn_386328278",
      "species": "Kraanvogel",
      "scientific_name": "Grus grus",
      "lat": 50.77112641042521,
      "lon": 5.912833213806152,
      "observed_on": "2026-02-19",
      "time": "15:22",
      "location_name": "Epen",
      "source": "waarneming_nl",
      "category": "bird",
      "rarity": 2,
      "rarity_label": "vrij_algemeen",
      "photo_url": "",
      "permalink": "https://waarneming.nl/observation/386328278/",
      "count": 200,
      "distance_km": 2.36
    },
    {
      "id": "wn_386323917",
      "species": "Kraanvogel",
      "scientific_name": "Grus grus",
      "lat": 50.78672100186333,
      "lon": 5.944970674754586,
      "observed_on": "2026-02-19",
      "time": "15:15",
      "location_name": "Rott",
      "source": "waarneming_nl",
      "category": "bird",
      "rarity": 2,
      "rarity_label": "vrij_algemeen",
      "photo_url": "",
      "permalink": "https://waarneming.nl/observation/386323917/",
      "count": 200,
      "distance_km": 4.77
    },
    {
      "id": "wn_386319101",
      "species": "Sleedoornpage",
      "scientific_name": "Thecla betulae",
      "lat": 50.77403149972222,
      "lon": 5.853308499722222,
      "observed_on": "2026-02-19",
      "time": "14:56",
      "location_name": "Slenaken - Maastrichterweg e.o.",
      "source": "waarneming_nl",
      "category": "insect",
      "rarity": 3,
      "rarity_label": "zeldzaam",
      "photo_url": "https://waarneming.nl/media/photo/144179211.jpg",
      "permalink": "https://waarneming.nl/observation/386319101/",
      "count": 1,
      "distance_km": 4.8
    },
    {
      "id": "wn_386314961",
      "species": "Das",
      "scientific_name": "Meles meles",
      "lat": 50.785642,
      "lon": 5.833297,
      "observed_on": "2026-02-19",
      "time": "12:17",
      "location_name": "Beutenaken - Terlinderveldweg e.o.",
      "source": "waarneming_nl",
      "category": "mammal",
      "rarity": 2,
      "rarity_label": "vrij_algemeen",
      "photo_url": "https://waarneming.nl/media/photo/144176700.jpg",
      "permalink": "https://waarneming.nl/observation/386314961/",
      "count": 1,
      "distance_km": 6.69
    },
    {
      "id": "wn_386337105",
      "species": "Kraanvogel",
      "scientific_name": "Grus grus",
      "lat": 50.81728771691932,
      "lon": 5.902976989746094,
      "observed_on": "2026-02-19",
      "time": "20:08",
      "location_name": "Gulpen",
      "source": "waarneming_nl",
      "category": "bird",
      "rarity": 2,
      "rarity_label": "vrij_algemeen",
      "photo_url": "",
      "permalink": "https://waarneming.nl/observation/386337105/",
      "count": 50,
      "distance_km": 7.5
    },
    {
      "id": "wn_386321235",
      "species": "Kraanvogel",
      "scientific_name": "Grus grus",
      "lat": 50.81742780425895,
      "lon": 5.950183868408203,
      "observed_on": "2026-02-19",
      "time": "15:28",
      "location_name": "Wahlwiller / Nijswiller - Kruisberg e.o.",
      "source": "waarneming_nl",
      "category": "bird",
      "rarity": 2,
      "rarity_label": "vrij_algemeen",
      "photo_url": "",
      "permalink": "https://waarneming.nl/observation/386321235/",
      "count": 250,
      "distance_km": 8.01
    },
    {
      "id": "wn_386309893",
      "species": "Rode Wouw",
      "scientific_name": "Milvus milvus",
      "lat": 50.83549118041992,
      "lon": 5.85230827331543,
      "observed_on": "2026-02-19",
      "time": "12:04",
      "location_name": "Gerendal",
      "source": "waarneming_nl",
      "category": "bird",
      "rarity": 2,
      "rarity_label": "vrij_algemeen",
      "photo_url": "https://waarneming.nl/media/photo/144177168.jpg",
      "permalink": "https://waarneming.nl/observation/386309893/",
      "count": 1,
      "distance_km": 10.33
    },
    {
      "id": "wn_386338091",
      "species": "Europese Rode Eekhoorn",
      "scientific_name": "Sciurus vulgaris",
      "lat": 50.838138580322266,
      "lon": 5.820813179016113,
      "observed_on": "2026-02-19",
      "time": "11:18",
      "location_name": "Sibbe - Hamsterreservaat",
      "source": "waarneming_nl",
      "category": "mammal",
      "rarity": 2,
      "rarity_label": "vrij_algemeen",
      "photo_url": "",
      "permalink": "https://waarneming.nl/observation/386338091/",
      "count": 1,
      "distance_km": 11.63
    },
    {
      "id": "wn_386338120",
      "species": "Blauwe Kiekendief",
      "scientific_name": "Circus cyaneus",
      "lat": 50.83034552451581,
      "lon": 5.742739923298359,
      "observed_on": "2026-02-19",
      "time": "09:26",
      "location_name": "Heer - Hamsterreservaat e.o. ",
      "source": "waarneming_nl",
      "category": "bird",
      "rarity": 2,
      "rarity_label": "vrij_algemeen",
      "photo_url": "",
      "permalink": "https://waarneming.nl/observation/386338120/",
      "count": 1,
      "distance_km": 14.77
    },
    {
      "id": "wn_386376933",
      "species": "Kraanvogel",
      "scientific_name": "Grus grus",
      "lat": 50.77035651778706,
      "lon": 5.908227503299486,
      "observed_on": "2026-02-20",
      "time": "15:00",
      "location_name": "Epen",
      "source": "waarneming_nl",
      "category": "bird",
      "rarity": 2,
      "rarity_label": "vrij_algemeen",
      "photo_url": "",
      "permalink": "https://waarneming.nl/observation/386376933/",
      "count": 50,
      "distance_km": 2.27
    },
    {
      "id": "wn_386404884",
      "species": "Das",
      "scientific_name": "Meles meles",
      "lat": 50.76901327127361,
      "lon": 5.934419707678589,
      "observed_on": "2026-02-20",
      "time": "20:28",
      "location_name": "Epen - Camerig",
      "source": "waarneming_nl",
      "category": "mammal",
      "rarity": 2,
      "rarity_label": "vrij_algemeen",
      "photo_url": "",
      "permalink": "https://waarneming.nl/observation/386404884/",
      "count": 5,
      "distance_km": 2.72
    },
    {
      "id": "wn_386404846",
      "species": "Das",
      "scientific_name": "Meles meles",
      "lat": 50.76901327127361,
      "lon": 5.934419707678589,
      "observed_on": "2026-02-20",
      "time": "20:28",
      "location_name": "Epen - Camerig",
      "source": "waarneming_nl",
      "category": "mammal",
      "rarity": 2,
      "rarity_label": "vrij_algemeen",
      "photo_url": "",
      "permalink": "https://waarneming.nl/observation/386404846/",
      "count": 5,
      "distance_km": 2.72
    },
    {
      "id": "wn_386404814",
      "species": "Das",
      "scientific_name": "Meles meles",
      "lat": 50.76901327127361,
      "lon": 5.934419707678589,
      "observed_on": "2026-02-20",
      "time": "20:28",
      "location_name": "Epen - Camerig",
      "source": "waarneming_nl",
      "category": "mammal",
      "rarity": 2,
      "rarity_label": "vrij_algemeen",
      "photo_url": "",
      "permalink": "https://waarneming.nl/observation/386404814/",
      "count": 5,
      "distance_km": 2.72
    },
    {
      "id": "wn_386404923",
      "species": "Das",
      "scientific_name": "Meles meles",
      "lat": 50.76904296875,
      "lon": 5.934395313262939,
      "observed_on": "2026-02-20",
      "time": "20:29",
      "location_name": "Epen - Camerig",
      "source": "waarneming_nl",
      "category": "mammal",
      "rarity": 2,
      "rarity_label": "vrij_algemeen",
      "photo_url": "",
      "permalink": "https://waarneming.nl/observation/386404923/",
      "count": 5,
      "distance_km": 2.73
    },
    {
      "id": "wn_386387582",
      "species": "Kraanvogel",
      "scientific_name": "Grus grus",
      "lat": 50.77526769946744,
      "lon": 5.906224250793457,
      "observed_on": "2026-02-20",
      "time": "14:45",
      "location_name": "Epen",
      "source": "waarneming_nl",
      "category": "bird",
      "rarity": 2,
      "rarity_label": "vrij_algemeen",
      "photo_url": "",
      "permalink": "https://waarneming.nl/observation/386387582/",
      "count": 20,
      "distance_km": 2.82
    },
    {
      "id": "wn_386404900",
      "species": "Das",
      "scientific_name": "Meles meles",
      "lat": 50.76618194580078,
      "lon": 5.947365283966064,
      "observed_on": "2026-02-20",
      "time": "22:59",
      "location_name": "Vaals - Zevenwegenbos",
      "source": "waarneming_nl",
      "category": "mammal",
      "rarity": 2,
      "rarity_label": "vrij_algemeen",
      "photo_url": "",
      "permalink": "https://waarneming.nl/observation/386404900/",
      "count": 1,
      "distance_km": 3.19
    },
    {
      "id": "wn_386404899",
      "species": "Das",
      "scientific_name": "Meles meles",
      "lat": 50.76377868652344,
      "lon": 5.952412128448486,
      "observed_on": "2026-02-20",
      "time": "23:00",
      "location_name": "Cottessen - Cottesserbeekdal",
      "source": "waarneming_nl",
      "category": "mammal",
      "rarity": 2,
      "rarity_label": "vrij_algemeen",
      "photo_url": "",
      "permalink": "https://waarneming.nl/observation/386404899/",
      "count": 1,
      "distance_km": 3.35
    },
    {
      "id": "wn_386381555",
      "species": "Kraanvogel",
      "scientific_name": "Grus grus",
      "lat": 50.78044385078422,
      "lon": 5.912882632630101,
      "observed_on": "2026-02-20",
      "time": "13:16",
      "location_name": "Epen",
      "source": "waarneming_nl",
      "category": "bird",
      "rarity": 2,
      "rarity_label": "vrij_algemeen",
      "photo_url": "",
      "permalink": "https://waarneming.nl/observation/386381555/",
      "count": 55,
      "distance_km": 3.39
    },
    {
      "id": "wn_386372365",
      "species": "Kraanvogel",
      "scientific_name": "Grus grus",
      "lat": 50.7844174,
      "lon": 5.925140599722223,
      "observed_on": "2026-02-20",
      "time": "14:49",
      "location_name": "Mechelen - Helle e.o.",
      "source": "waarneming_nl",
      "category": "bird",
      "rarity": 2,
      "rarity_label": "vrij_algemeen",
      "photo_url": "https://waarneming.nl/media/photo/144206058.jpg",
      "permalink": "https://waarneming.nl/observation/386372365/",
      "count": 1,
      "distance_km": 3.97
    },
    {
      "id": "wn_386404902",
      "species": "Das",
      "scientific_name": "Meles meles",
      "lat": 50.76679992675781,
      "lon": 5.96148157119751,
      "observed_on": "2026-02-20",
      "time": "22:41",
      "location_name": "Vaals - Kerperbos",
      "source": "waarneming_nl",
      "category": "mammal",
      "rarity": 2,
      "rarity_label": "vrij_algemeen",
      "photo_url": "",
      "permalink": "https://waarneming.nl/observation/386404902/",
      "count": 1,
      "distance_km": 4.07
    },
    {
      "id": "wn_386398824",
      "species": "Kraanvogel",
      "scientific_name": "Grus grus",
      "lat": 50.766197204589844,
      "lon": 5.962452411651611,
      "observed_on": "2026-02-20",
      "time": "13:18",
      "location_name": "Vaals - Kerperbos",
      "source": "waarneming_nl",
      "category": "bird",
      "rarity": 2,
      "rarity_label": "vrij_algemeen",
      "photo_url": "",
      "permalink": "https://waarneming.nl/observation/386398824/",
      "count": 48,
      "distance_km": 4.11
    },
    {
      "id": "wn_386369843",
      "species": "Kraanvogel",
      "scientific_name": "Grus grus",
      "lat": 50.76626205444336,
      "lon": 5.962460517883301,
      "observed_on": "2026-02-20",
      "time": "13:16",
      "location_name": "Vaals - Kerperbos",
      "source": "waarneming_nl",
      "category": "bird",
      "rarity": 2,
      "rarity_label": "vrij_algemeen",
      "photo_url": "",
      "permalink": "https://waarneming.nl/observation/386369843/",
      "count": 48,
      "distance_km": 4.11
    },
    {
      "id": "wn_386402200",
      "species": "Kortsnavelboomkruiper",
      "scientific_name": "Certhia familiaris macrodactyla",
      "lat": 50.76632800045252,
      "lon": 5.962525658759403,
      "observed_on": "2026-02-20",
      "time": "15:24",
      "location_name": "Vaals - Kerperbos",
      "source": "waarneming_nl",
      "category": "bird",
      "rarity": 3,
      "rarity_label": "zeldzaam",
      "photo_url": "https://waarneming.nl/media/photo/144220870.jpg",
      "permalink": "https://waarneming.nl/observation/386402200/",
      "count": 1,
      "distance_km": 4.12
    },
    {
      "id": "wn_386388818",
      "species": "Kortsnavelboomkruiper",
      "scientific_name": "Certhia familiaris macrodactyla",
      "lat": 50.76632800045252,
      "lon": 5.962525658759403,
      "observed_on": "2026-02-20",
      "time": "15:24",
      "location_name": "Vaals - Kerperbos",
      "source": "waarneming_nl",
      "category": "bird",
      "rarity": 3,
      "rarity_label": "zeldzaam",
      "photo_url": "",
      "permalink": "https://waarneming.nl/observation/386388818/",
      "count": 1,
      "distance_km": 4.12
    },
    {
      "id": "wn_386404912",
      "species": "Wild Zwijn",
      "scientific_name": "Sus scrofa",
      "lat": 50.76796340942383,
      "lon": 5.961912155151367,
      "observed_on": "2026-02-20",
      "time": "21:35",
      "location_name": "Vaals - Kerperbos",
      "source": "waarneming_nl",
      "category": "mammal",
      "rarity": 2,
      "rarity_label": "vrij_algemeen",
      "photo_url": "",
      "permalink": "https://waarneming.nl/observation/386404912/",
      "count": 5,
      "distance_km": 4.16
    },
    {
      "id": "wn_386404883",
      "species": "Wild Zwijn",
      "scientific_name": "Sus scrofa",
      "lat": 50.76798439811975,
      "lon": 5.961891120168923,
      "observed_on": "2026-02-20",
      "time": "21:35",
      "location_name": "Vaals - Kerperbos",
      "source": "waarneming_nl",
      "category": "mammal",
      "rarity": 2,
      "rarity_label": "vrij_algemeen",
      "photo_url": "",
      "permalink": "https://waarneming.nl/observation/386404883/",
      "count": 5,
      "distance_km": 4.16
    },
    {
      "id": "wn_386404834",
      "species": "Wild Zwijn",
      "scientific_name": "Sus scrofa",
      "lat": 50.76811477692053,
      "lon": 5.961778834462166,
      "observed_on": "2026-02-20",
      "time": "21:36",
      "location_name": "Vaals - Kerperbos",
      "source": "waarneming_nl",
      "category": "mammal",
      "rarity": 2,
      "rarity_label": "vrij_algemeen",
      "photo_url": "",
      "permalink": "https://waarneming.nl/observation/386404834/",
      "count": 5,
      "distance_km": 4.16
    },
    {
      "id": "wn_386404819",
      "species": "Wild Zwijn",
      "scientific_name": "Sus scrofa",
      "lat": 50.76798439811975,
      "lon": 5.961891120168923,
      "observed_on": "2026-02-20",
      "time": "21:35",
      "location_name": "Vaals - Kerperbos",
      "source": "waarneming_nl",
      "category": "mammal",
      "rarity": 2,
      "rarity_label": "vrij_algemeen",
      "photo_url": "",
      "permalink": "https://waarneming.nl/observation/386404819/",
      "count": 5,
      "distance_km": 4.16
    },
    {
      "id": "wn_386398825",
      "species": "Kortsnavelboomkruiper",
      "scientific_name": "Certhia familiaris macrodactyla",
      "lat": 50.76630783081055,
      "lon": 5.96483325958252,
      "observed_on": "2026-02-20",
      "time": "13:10",
      "location_name": "Vaals - Kerperbos",
      "source": "waarneming_nl",
      "category": "bird",
      "rarity": 3,
      "rarity_label": "zeldzaam",
      "photo_url": "",
      "permalink": "https://waarneming.nl/observation/386398825/",
      "count": 1,
      "distance_km": 4.26
    },
    {
      "id": "wn_386389156",
      "species": "Kortsnavelboomkruiper",
      "scientific_name": "Certhia familiaris macrodactyla",
      "lat": 50.76646423339844,
      "lon": 5.964675903320312,
      "observed_on": "2026-02-20",
      "time": "13:13",
      "location_name": "Vaals - Kerperbos",
      "source": "waarneming_nl",
      "category": "bird",
      "rarity": 3,
      "rarity_label": "zeldzaam",
      "photo_url": "",
      "permalink": "https://waarneming.nl/observation/386389156/",
      "count": 1,
      "distance_km": 4.26
    },
    {
      "id": "wn_386369396",
      "species": "Kortsnavelboomkruiper",
      "scientific_name": "Certhia familiaris macrodactyla",
      "lat": 50.76646423339844,
      "lon": 5.964675903320312,
      "observed_on": "2026-02-20",
      "time": "13:13",
      "location_name": "Vaals - Kerperbos",
      "source": "waarneming_nl",
      "category": "bird",
      "rarity": 3,
      "rarity_label": "zeldzaam",
      "photo_url": "",
      "permalink": "https://waarneming.nl/observation/386369396/",
      "count": 1,
      "distance_km": 4.26
    },
    {
      "id": "wn_386369393",
      "species": "Kleine Bonte Specht",
      "scientific_name": "Dryobates minor",
      "lat": 50.76646423339844,
      "lon": 5.964675903320312,
      "observed_on": "2026-02-20",
      "time": "13:14",
      "location_name": "Vaals - Kerperbos",
      "source": "waarneming_nl",
      "category": "bird",
      "rarity": 2,
      "rarity_label": "vrij_algemeen",
      "photo_url": "",
      "permalink": "https://waarneming.nl/observation/386369393/",
      "count": 1,
      "distance_km": 4.26
    },
    {
      "id": "wn_386364671",
      "species": "Kraanvogel",
      "scientific_name": "Grus grus",
      "lat": 50.76643753051758,
      "lon": 5.96473503112793,
      "observed_on": "2026-02-20",
      "time": "13:16",
      "location_name": "Vaals - Kerperbos",
      "source": "waarneming_nl",
      "category": "bird",
      "rarity": 2,
      "rarity_label": "vrij_algemeen",
      "photo_url": "",
      "permalink": "https://waarneming.nl/observation/386364671/",
      "count": 75,
      "distance_km": 4.26
    },
    {
      "id": "wn_386383678",
      "species": "Kortsnavelboomkruiper",
      "scientific_name": "Certhia familiaris macrodactyla",
      "lat": 50.76649475097656,
      "lon": 5.964797019958496,
      "observed_on": "2026-02-20",
      "time": "12:47",
      "location_name": "Vaals - Kerperbos",
      "source": "waarneming_nl",
      "category": "bird",
      "rarity": 3,
      "rarity_label": "zeldzaam",
      "photo_url": "https://waarneming.nl/media/photo/144220495.jpg",
      "permalink": "https://waarneming.nl/observation/386383678/",
      "count": 2,
      "distance_km": 4.27
    },
    {
      "id": "wn_386399860",
      "species": "Kortsnavelboomkruiper",
      "scientific_name": "Certhia familiaris macrodactyla",
      "lat": 50.76641845703125,
      "lon": 5.964799880981445,
      "observed_on": "2026-02-20",
      "time": "13:08",
      "location_name": "Vaals - Kerperbos",
      "source": "waarneming_nl",
      "category": "bird",
      "rarity": 3,
      "rarity_label": "zeldzaam",
      "photo_url": "",
      "permalink": "https://waarneming.nl/observation/386399860/",
      "count": 1,
      "distance_km": 4.27
    },
    {
      "id": "wn_386399858",
      "species": "Kleine Bonte Specht",
      "scientific_name": "Dryobates minor",
      "lat": 50.76642608642578,
      "lon": 5.964799404144287,
      "observed_on": "2026-02-20",
      "time": "13:08",
      "location_name": "Vaals - Kerperbos",
      "source": "waarneming_nl",
      "category": "bird",
      "rarity": 2,
      "rarity_label": "vrij_algemeen",
      "photo_url": "",
      "permalink": "https://waarneming.nl/observation/386399858/",
      "count": 1,
      "distance_km": 4.27
    },
    {
      "id": "wn_386398826",
      "species": "Kleine Bonte Specht",
      "scientific_name": "Dryobates minor",
      "lat": 50.76629638671875,
      "lon": 5.964966773986816,
      "observed_on": "2026-02-20",
      "time": "13:08",
      "location_name": "Vaals - Kerperbos",
      "source": "waarneming_nl",
      "category": "bird",
      "rarity": 2,
      "rarity_label": "vrij_algemeen",
      "photo_url": "",
      "permalink": "https://waarneming.nl/observation/386398826/",
      "count": 1,
      "distance_km": 4.27
    },
    {
      "id": "wn_386389154",
      "species": "Kraanvogel",
      "scientific_name": "Grus grus",
      "lat": 50.7664909362793,
      "lon": 5.964776992797852,
      "observed_on": "2026-02-20",
      "time": "13:17",
      "location_name": "Vaals - Kerperbos",
      "source": "waarneming_nl",
      "category": "bird",
      "rarity": 2,
      "rarity_label": "vrij_algemeen",
      "photo_url": "",
      "permalink": "https://waarneming.nl/observation/386389154/",
      "count": 75,
      "distance_km": 4.27
    },
    {
      "id": "wn_386383178",
      "species": "Kortsnavelboomkruiper",
      "scientific_name": "Certhia familiaris macrodactyla",
      "lat": 50.76649475097656,
      "lon": 5.964797019958496,
      "observed_on": "2026-02-20",
      "time": "12:47",
      "location_name": "Vaals - Kerperbos",
      "source": "waarneming_nl",
      "category": "bird",
      "rarity": 3,
      "rarity_label": "zeldzaam",
      "photo_url": "",
      "permalink": "https://waarneming.nl/observation/386383178/",
      "count": 2,
      "distance_km": 4.27
    },
    {
      "id": "wn_386369856",
      "species": "Kortsnavelboomkruiper",
      "scientific_name": "Certhia familiaris macrodactyla",
      "lat": 50.76649475097656,
      "lon": 5.964749813079834,
      "observed_on": "2026-02-20",
      "time": "12:47",
      "location_name": "Vaals - Kerperbos",
      "source": "waarneming_nl",
      "category": "bird",
      "rarity": 3,
      "rarity_label": "zeldzaam",
      "photo_url": "",
      "permalink": "https://waarneming.nl/observation/386369856/",
      "count": 1,
      "distance_km": 4.27
    },
    {
      "id": "wn_386369391",
      "species": "Kraanvogel",
      "scientific_name": "Grus grus",
      "lat": 50.7664909362793,
      "lon": 5.964776992797852,
      "observed_on": "2026-02-20",
      "time": "13:17",
      "location_name": "Vaals - Kerperbos",
      "source": "waarneming_nl",
      "category": "bird",
      "rarity": 2,
      "rarity_label": "vrij_algemeen",
      "photo_url": "",
      "permalink": "https://waarneming.nl/observation/386369391/",
      "count": 75,
      "distance_km": 4.27
    },
    {
      "id": "wn_386364718",
      "species": "Kraanvogel",
      "scientific_name": "Grus grus",
      "lat": 50.76657577692297,
      "lon": 5.964792805200917,
      "observed_on": "2026-02-20",
      "time": "13:15",
      "location_name": "Vaals - Kerperbos",
      "source": "waarneming_nl",
      "category": "bird",
      "rarity": 2,
      "rarity_label": "vrij_algemeen",
      "photo_url": "",
      "permalink": "https://waarneming.nl/observation/386364718/",
      "count": 75,
      "distance_km": 4.27
    },
    {
      "id": "wn_386399855",
      "species": "Kraanvogel",
      "scientific_name": "Grus grus",
      "lat": 50.76651382446289,
      "lon": 5.964926242828369,
      "observed_on": "2026-02-20",
      "time": "13:16",
      "location_name": "Vaals - Kerperbos",
      "source": "waarneming_nl",
      "category": "bird",
      "rarity": 2,
      "rarity_label": "vrij_algemeen",
      "photo_url": "",
      "permalink": "https://waarneming.nl/observation/386399855/",
      "count": 1,
      "distance_km": 4.28
    },
    {
      "id": "wn_386383676",
      "species": "Kleine Bonte Specht",
      "scientific_name": "Dryobates minor",
      "lat": 50.76636505126953,
      "lon": 5.965075016021729,
      "observed_on": "2026-02-20",
      "time": "12:59",
      "location_name": "Vaals - Kerperbos",
      "source": "waarneming_nl",
      "category": "bird",
      "rarity": 2,
      "rarity_label": "vrij_algemeen",
      "photo_url": "",
      "permalink": "https://waarneming.nl/observation/386383676/",
      "count": 1,
      "distance_km": 4.28
    },
    {
      "id": "wn_386383177",
      "species": "Kleine Bonte Specht",
      "scientific_name": "Dryobates minor",
      "lat": 50.76636505126953,
      "lon": 5.965075016021729,
      "observed_on": "2026-02-20",
      "time": "12:59",
      "location_name": "Vaals - Kerperbos",
      "source": "waarneming_nl",
      "category": "bird",
      "rarity": 2,
      "rarity_label": "vrij_algemeen",
      "photo_url": "",
      "permalink": "https://waarneming.nl/observation/386383177/",
      "count": 1,
      "distance_km": 4.28
    },
    {
      "id": "wn_386369868",
      "species": "Kleine Bonte Specht",
      "scientific_name": "Dryobates minor",
      "lat": 50.766326904296875,
      "lon": 5.965064525604248,
      "observed_on": "2026-02-20",
      "time": "12:58",
      "location_name": "Vaals - Kerperbos",
      "source": "waarneming_nl",
      "category": "bird",
      "rarity": 2,
      "rarity_label": "vrij_algemeen",
      "photo_url": "",
      "permalink": "https://waarneming.nl/observation/386369868/",
      "count": 1,
      "distance_km": 4.28
    },
    {
      "id": "wn_386404909",
      "species": "Das",
      "scientific_name": "Meles meles",
      "lat": 50.77016830444336,
      "lon": 5.961830139160156,
      "observed_on": "2026-02-20",
      "time": "21:49",
      "location_name": "Vaals - Kerperbos",
      "source": "waarneming_nl",
      "category": "mammal",
      "rarity": 2,
      "rarity_label": "vrij_algemeen",
      "photo_url": "",
      "permalink": "https://waarneming.nl/observation/386404909/",
      "count": 2,
      "distance_km": 4.28
    },
    {
      "id": "wn_386404882",
      "species": "Das",
      "scientific_name": "Meles meles",
      "lat": 50.77011343032825,
      "lon": 5.961796938111083,
      "observed_on": "2026-02-20",
      "time": "21:50",
      "location_name": "Vaals - Kerperbos",
      "source": "waarneming_nl",
      "category": "mammal",
      "rarity": 2,
      "rarity_label": "vrij_algemeen",
      "photo_url": "",
      "permalink": "https://waarneming.nl/observation/386404882/",
      "count": 2,
      "distance_km": 4.28
    },
    {
      "id": "wn_386404845",
      "species": "Das",
      "scientific_name": "Meles meles",
      "lat": 50.77011343032825,
      "lon": 5.961796938111083,
      "observed_on": "2026-02-20",
      "time": "21:50",
      "location_name": "Vaals - Kerperbos",
      "source": "waarneming_nl",
      "category": "mammal",
      "rarity": 2,
      "rarity_label": "vrij_algemeen",
      "photo_url": "",
      "permalink": "https://waarneming.nl/observation/386404845/",
      "count": 2,
      "distance_km": 4.28
    },
    {
      "id": "wn_386404821",
      "species": "Das",
      "scientific_name": "Meles meles",
      "lat": 50.77011343032825,
      "lon": 5.961796938111083,
      "observed_on": "2026-02-20",
      "time": "21:50",
      "location_name": "Vaals - Kerperbos",
      "source": "waarneming_nl",
      "category": "mammal",
      "rarity": 2,
      "rarity_label": "vrij_algemeen",
      "photo_url": "",
      "permalink": "https://waarneming.nl/observation/386404821/",
      "count": 2,
      "distance_km": 4.28
    },
    {
      "id": "wn_386387867",
      "species": "Kraanvogel",
      "scientific_name": "Grus grus",
      "lat": 50.7789306640625,
      "lon": 5.974136829376221,
      "observed_on": "2026-02-20",
      "time": "16:26",
      "location_name": "Harles e.o.",
      "source": "waarneming_nl",
      "category": "bird",
      "rarity": 2,
      "rarity_label": "vrij_algemeen",
      "photo_url": "",
      "permalink": "https://waarneming.nl/observation/386387867/",
      "count": 150,
      "distance_km": 5.54
    },
    {
      "id": "wn_386389150",
      "species": "Kraanvogel",
      "scientific_name": "Grus grus",
      "lat": 50.811119079589844,
      "lon": 5.916769981384277,
      "observed_on": "2026-02-20",
      "time": "14:16",
      "location_name": "Partij ",
      "source": "waarneming_nl",
      "category": "bird",
      "rarity": 2,
      "rarity_label": "vrij_algemeen",
      "photo_url": "",
      "permalink": "https://waarneming.nl/observation/386389150/",
      "count": 40,
      "distance_km": 6.81
    },
    {
      "id": "wn_386369384",
      "species": "Kraanvogel",
      "scientific_name": "Grus grus",
      "lat": 50.811119079589844,
      "lon": 5.916769981384277,
      "observed_on": "2026-02-20",
      "time": "14:16",
      "location_name": "Partij ",
      "source": "waarneming_nl",
      "category": "bird",
      "rarity": 2,
      "rarity_label": "vrij_algemeen",
      "photo_url": "",
      "permalink": "https://waarneming.nl/observation/386369384/",
      "count": 40,
      "distance_km": 6.81
    },
    {
      "id": "wn_386365199",
      "species": "Kraanvogel",
      "scientific_name": "Grus grus",
      "lat": 50.77336362304923,
      "lon": 6.003020128996147,
      "observed_on": "2026-02-20",
      "time": "13:19",
      "location_name": "Vaals - Hoog Vaals e.o.",
      "source": "waarneming_nl",
      "category": "bird",
      "rarity": 2,
      "rarity_label": "vrij_algemeen",
      "photo_url": "",
      "permalink": "https://waarneming.nl/observation/386365199/",
      "count": 70,
      "distance_km": 7.04
    },
    {
      "id": "wn_386393072",
      "species": "Rode Wouw",
      "scientific_name": "Milvus milvus",
      "lat": 50.81716722836427,
      "lon": 5.929898752053333,
      "observed_on": "2026-02-20",
      "time": "12:45",
      "location_name": "Wahlwiller / Nijswiller - Kruisberg e.o.",
      "source": "waarneming_nl",
      "category": "bird",
      "rarity": 2,
      "rarity_label": "vrij_algemeen",
      "photo_url": "",
      "permalink": "https://waarneming.nl/observation/386393072/",
      "count": 1,
      "distance_km": 7.6
    },
    {
      "id": "wn_386385465",
      "species": "Rode Wouw",
      "scientific_name": "Milvus milvus",
      "lat": 50.81716722836427,
      "lon": 5.929898752053333,
      "observed_on": "2026-02-20",
      "time": "12:45",
      "location_name": "Wahlwiller / Nijswiller - Kruisberg e.o.",
      "source": "waarneming_nl",
      "category": "bird",
      "rarity": 2,
      "rarity_label": "vrij_algemeen",
      "photo_url": "",
      "permalink": "https://waarneming.nl/observation/386385465/",
      "count": 1,
      "distance_km": 7.6
    },
    {
      "id": "wn_386365100",
      "species": "Kraanvogel",
      "scientific_name": "Grus grus",
      "lat": 50.7597565,
      "lon": 6.017370600000049,
      "observed_on": "2026-02-20",
      "time": "13:17",
      "location_name": "Vaals - Vaalserberg",
      "source": "waarneming_nl",
      "category": "bird",
      "rarity": 2,
      "rarity_label": "vrij_algemeen",
      "photo_url": "https://waarneming.nl/media/photo/144202024.jpg",
      "permalink": "https://waarneming.nl/observation/386365100/",
      "count": 40,
      "distance_km": 7.63
    },
    {
      "id": "wn_386369874",
      "species": "Kraanvogel",
      "scientific_name": "Grus grus",
      "lat": 50.816998503017885,
      "lon": 5.936050415039062,
      "observed_on": "2026-02-20",
      "time": "14:21",
      "location_name": "Wahlwiller / Nijswiller - Kruisberg e.o.",
      "source": "waarneming_nl",
      "category": "bird",
      "rarity": 2,
      "rarity_label": "vrij_algemeen",
      "photo_url": "",
      "permalink": "https://waarneming.nl/observation/386369874/",
      "count": 42,
      "distance_km": 7.67
    },
    {
      "id": "wn_386367181",
      "species": "Kraanvogel",
      "scientific_name": "Grus grus",
      "lat": 50.818112149683756,
      "lon": 5.890308734902646,
      "observed_on": "2026-02-20",
      "time": null,
      "location_name": "Gulpen",
      "source": "waarneming_nl",
      "category": "bird",
      "rarity": 2,
      "rarity_label": "vrij_algemeen",
      "photo_url": "",
      "permalink": "https://waarneming.nl/observation/386367181/",
      "count": 45,
      "distance_km": 7.7
    },
    {
      "id": "wn_386392936",
      "species": "Rode Wouw",
      "scientific_name": "Milvus milvus",
      "lat": 50.81792068481445,
      "lon": 5.931843280792236,
      "observed_on": "2026-02-20",
      "time": "12:44",
      "location_name": "Wahlwiller / Nijswiller - Kruisberg e.o.",
      "source": "waarneming_nl",
      "category": "bird",
      "rarity": 2,
      "rarity_label": "vrij_algemeen",
      "photo_url": "",
      "permalink": "https://waarneming.nl/observation/386392936/",
      "count": 1,
      "distance_km": 7.71
    },
    {
      "id": "wn_386382738",
      "species": "Rode Wouw",
      "scientific_name": "Milvus milvus",
      "lat": 50.81793551666666,
      "lon": 5.9318677,
      "observed_on": "2026-02-20",
      "time": "12:44",
      "location_name": "Wahlwiller / Nijswiller - Kruisberg e.o.",
      "source": "waarneming_nl",
      "category": "bird",
      "rarity": 2,
      "rarity_label": "vrij_algemeen",
      "photo_url": "",
      "permalink": "https://waarneming.nl/observation/386382738/",
      "count": 1,
      "distance_km": 7.71
    },
    {
      "id": "wn_386381834",
      "species": "Rode Wouw",
      "scientific_name": "Milvus milvus",
      "lat": 50.81792068481445,
      "lon": 5.931843280792236,
      "observed_on": "2026-02-20",
      "time": "12:44",
      "location_name": "Wahlwiller / Nijswiller - Kruisberg e.o.",
      "source": "waarneming_nl",
      "category": "bird",
      "rarity": 2,
      "rarity_label": "vrij_algemeen",
      "photo_url": "",
      "permalink": "https://waarneming.nl/observation/386381834/",
      "count": 1,
      "distance_km": 7.71
    },
    {
      "id": "wn_386373082",
      "species": "Rode Wouw",
      "scientific_name": "Milvus milvus",
      "lat": 50.817955017089844,
      "lon": 5.931880474090576,
      "observed_on": "2026-02-20",
      "time": "12:45",
      "location_name": "Wahlwiller / Nijswiller - Kruisberg e.o.",
      "source": "waarneming_nl",
      "category": "bird",
      "rarity": 2,
      "rarity_label": "vrij_algemeen",
      "photo_url": "",
      "permalink": "https://waarneming.nl/observation/386373082/",
      "count": 1,
      "distance_km": 7.71
    },
    {
      "id": "wn_386398628",
      "species": "Blauwe Kiekendief",
      "scientific_name": "Circus cyaneus",
      "lat": 50.81789779663086,
      "lon": 5.939773559570312,
      "observed_on": "2026-02-20",
      "time": "14:06",
      "location_name": "Wahlwiller / Nijswiller - Kruisberg e.o.",
      "source": "waarneming_nl",
      "category": "bird",
      "rarity": 2,
      "rarity_label": "vrij_algemeen",
      "photo_url": "",
      "permalink": "https://waarneming.nl/observation/386398628/",
      "count": 1,
      "distance_km": 7.83
    },
    {
      "id": "wn_386398118",
      "species": "Blauwe Kiekendief",
      "scientific_name": "Circus cyaneus",
      "lat": 50.81789779663086,
      "lon": 5.939773559570312,
      "observed_on": "2026-02-20",
      "time": "14:06",
      "location_name": "Wahlwiller / Nijswiller - Kruisberg e.o.",
      "source": "waarneming_nl",
      "category": "bird",
      "rarity": 2,
      "rarity_label": "vrij_algemeen",
      "photo_url": "",
      "permalink": "https://waarneming.nl/observation/386398118/",
      "count": 1,
      "distance_km": 7.83
    },
    {
      "id": "wn_386383651",
      "species": "Kraanvogel",
      "scientific_name": "Grus grus",
      "lat": 50.817970275878906,
      "lon": 5.939562320709229,
      "observed_on": "2026-02-20",
      "time": "16:00",
      "location_name": "Wahlwiller / Nijswiller - Kruisberg e.o.",
      "source": "waarneming_nl",
      "category": "bird",
      "rarity": 2,
      "rarity_label": "vrij_algemeen",
      "photo_url": "https://waarneming.nl/media/photo/144220474.jpg",
      "permalink": "https://waarneming.nl/observation/386383651/",
      "count": 65,
      "distance_km": 7.84
    },
    {
      "id": "wn_386398823",
      "species": "Rode Wouw",
      "scientific_name": "Milvus milvus",
      "lat": 50.817955017089844,
      "lon": 5.939754009246826,
      "observed_on": "2026-02-20",
      "time": "13:59",
      "location_name": "Wahlwiller / Nijswiller - Kruisberg e.o.",
      "source": "waarneming_nl",
      "category": "bird",
      "rarity": 2,
      "rarity_label": "vrij_algemeen",
      "photo_url": "",
      "permalink": "https://waarneming.nl/observation/386398823/",
      "count": 1,
      "distance_km": 7.84
    },
    {
      "id": "wn_386378568",
      "species": "Kraanvogel",
      "scientific_name": "Grus grus",
      "lat": 50.817970275878906,
      "lon": 5.939562320709229,
      "observed_on": "2026-02-20",
      "time": "16:00",
      "location_name": "Wahlwiller / Nijswiller - Kruisberg e.o.",
      "source": "waarneming_nl",
      "category": "bird",
      "rarity": 2,
      "rarity_label": "vrij_algemeen",
      "photo_url": "",
      "permalink": "https://waarneming.nl/observation/386378568/",
      "count": 65,
      "distance_km": 7.84
    },
    {
      "id": "wn_386373094",
      "species": "Blauwe Kiekendief",
      "scientific_name": "Circus cyaneus",
      "lat": 50.81797790527344,
      "lon": 5.939515113830566,
      "observed_on": "2026-02-20",
      "time": "11:59",
      "location_name": "Wahlwiller / Nijswiller - Kruisberg e.o.",
      "source": "waarneming_nl",
      "category": "bird",
      "rarity": 2,
      "rarity_label": "vrij_algemeen",
      "photo_url": "",
      "permalink": "https://waarneming.nl/observation/386373094/",
      "count": 1,
      "distance_km": 7.84
    },
    {
      "id": "wn_386369829",
      "species": "Rode Wouw",
      "scientific_name": "Milvus milvus",
      "lat": 50.817962646484375,
      "lon": 5.939760208129883,
      "observed_on": "2026-02-20",
      "time": "13:57",
      "location_name": "Wahlwiller / Nijswiller - Kruisberg e.o.",
      "source": "waarneming_nl",
      "category": "bird",
      "rarity": 2,
      "rarity_label": "vrij_algemeen",
      "photo_url": "",
      "permalink": "https://waarneming.nl/observation/386369829/",
      "count": 1,
      "distance_km": 7.84
    },
    {
      "id": "wn_386383641",
      "species": "Kraanvogel",
      "scientific_name": "Grus grus",
      "lat": 50.81797790527344,
      "lon": 5.940009593963623,
      "observed_on": "2026-02-20",
      "time": "16:30",
      "location_name": "Wahlwiller / Nijswiller - Kruisberg e.o.",
      "source": "waarneming_nl",
      "category": "bird",
      "rarity": 2,
      "rarity_label": "vrij_algemeen",
      "photo_url": "https://waarneming.nl/media/photo/144220466.jpg",
      "permalink": "https://waarneming.nl/observation/386383641/",
      "count": 102,
      "distance_km": 7.85
    },
    {
      "id": "wn_386398814",
      "species": "Kraanvogel",
      "scientific_name": "Grus grus",
      "lat": 50.81797409057617,
      "lon": 5.939950942993164,
      "observed_on": "2026-02-20",
      "time": "14:21",
      "location_name": "Wahlwiller / Nijswiller - Kruisberg e.o.",
      "source": "waarneming_nl",
      "category": "bird",
      "rarity": 2,
      "rarity_label": "vrij_algemeen",
      "photo_url": "",
      "permalink": "https://waarneming.nl/observation/386398814/",
      "count": 42,
      "distance_km": 7.85
    },
    {
      "id": "wn_386381274",
      "species": "Kraanvogel",
      "scientific_name": "Grus grus",
      "lat": 50.81797790527344,
      "lon": 5.940009593963623,
      "observed_on": "2026-02-20",
      "time": "16:30",
      "location_name": "Wahlwiller / Nijswiller - Kruisberg e.o.",
      "source": "waarneming_nl",
      "category": "bird",
      "rarity": 2,
      "rarity_label": "vrij_algemeen",
      "photo_url": "",
      "permalink": "https://waarneming.nl/observation/386381274/",
      "count": 102,
      "distance_km": 7.85
    },
    {
      "id": "wn_386371731",
      "species": "Kraanvogel",
      "scientific_name": "Grus grus",
      "lat": 50.818209574276764,
      "lon": 5.938711166381836,
      "observed_on": "2026-02-20",
      "time": "14:45",
      "location_name": "Wahlwiller / Nijswiller - Kruisberg e.o.",
      "source": "waarneming_nl",
      "category": "bird",
      "rarity": 2,
      "rarity_label": "vrij_algemeen",
      "photo_url": "",
      "permalink": "https://waarneming.nl/observation/386371731/",
      "count": 52,
      "distance_km": 7.85
    },
    {
      "id": "wn_386369798",
      "species": "Kraanvogel",
      "scientific_name": "Grus grus",
      "lat": 50.81797409057617,
      "lon": 5.939940929412842,
      "observed_on": "2026-02-20",
      "time": "14:21",
      "location_name": "Wahlwiller / Nijswiller - Kruisberg e.o.",
      "source": "waarneming_nl",
      "category": "bird",
      "rarity": 2,
      "rarity_label": "vrij_algemeen",
      "photo_url": "",
      "permalink": "https://waarneming.nl/observation/386369798/",
      "count": 42,
      "distance_km": 7.85
    },
    {
      "id": "wn_386392939",
      "species": "Blauwe Kiekendief",
      "scientific_name": "Circus cyaneus",
      "lat": 50.818375783447976,
      "lon": 5.941409133374691,
      "observed_on": "2026-02-20",
      "time": "11:57",
      "location_name": "Wahlwiller / Nijswiller - Kruisberg e.o.",
      "source": "waarneming_nl",
      "category": "bird",
      "rarity": 2,
      "rarity_label": "vrij_algemeen",
      "photo_url": "",
      "permalink": "https://waarneming.nl/observation/386392939/",
      "count": 1,
      "distance_km": 7.92
    },
    {
      "id": "wn_386381840",
      "species": "Blauwe Kiekendief",
      "scientific_name": "Circus cyaneus",
      "lat": 50.818375783447976,
      "lon": 5.941409133374691,
      "observed_on": "2026-02-20",
      "time": "11:57",
      "location_name": "Wahlwiller / Nijswiller - Kruisberg e.o.",
      "source": "waarneming_nl",
      "category": "bird",
      "rarity": 2,
      "rarity_label": "vrij_algemeen",
      "photo_url": "",
      "permalink": "https://waarneming.nl/observation/386381840/",
      "count": 1,
      "distance_km": 7.92
    },
    {
      "id": "wn_386383654",
      "species": "Rode Wouw",
      "scientific_name": "Milvus milvus",
      "lat": 50.81949969213152,
      "lon": 5.9375024959445,
      "observed_on": "2026-02-20",
      "time": "15:41",
      "location_name": "Wahlwiller / Nijswiller - Kruisberg e.o.",
      "source": "waarneming_nl",
      "category": "bird",
      "rarity": 2,
      "rarity_label": "vrij_algemeen",
      "photo_url": "",
      "permalink": "https://waarneming.nl/observation/386383654/",
      "count": 1,
      "distance_km": 7.97
    },
    {
      "id": "wn_386383113",
      "species": "Rode Wouw",
      "scientific_name": "Milvus milvus",
      "lat": 50.81949969213152,
      "lon": 5.9375024959445,
      "observed_on": "2026-02-20",
      "time": "15:41",
      "location_name": "Wahlwiller / Nijswiller - Kruisberg e.o.",
      "source": "waarneming_nl",
      "category": "bird",
      "rarity": 2,
      "rarity_label": "vrij_algemeen",
      "photo_url": "",
      "permalink": "https://waarneming.nl/observation/386383113/",
      "count": 1,
      "distance_km": 7.97
    },
    {
      "id": "wn_386383652",
      "species": "Rode Wouw",
      "scientific_name": "Milvus milvus",
      "lat": 50.81969795139186,
      "lon": 5.936853736639023,
      "observed_on": "2026-02-20",
      "time": "15:52",
      "location_name": "Wahlwiller / Nijswiller - Kruisberg e.o.",
      "source": "waarneming_nl",
      "category": "bird",
      "rarity": 2,
      "rarity_label": "vrij_algemeen",
      "photo_url": "https://waarneming.nl/media/photo/144220476.jpg",
      "permalink": "https://waarneming.nl/observation/386383652/",
      "count": 1,
      "distance_km": 7.98
    },
    {
      "id": "wn_386383106",
      "species": "Rode Wouw",
      "scientific_name": "Milvus milvus",
      "lat": 50.81969795139186,
      "lon": 5.936853736639023,
      "observed_on": "2026-02-20",
      "time": "15:52",
      "location_name": "Wahlwiller / Nijswiller - Kruisberg e.o.",
      "source": "waarneming_nl",
      "category": "bird",
      "rarity": 2,
      "rarity_label": "vrij_algemeen",
      "photo_url": "",
      "permalink": "https://waarneming.nl/observation/386383106/",
      "count": 1,
      "distance_km": 7.98
    },
    {
      "id": "wn_386372738",
      "species": "Kraanvogel",
      "scientific_name": "Grus grus",
      "lat": 50.830228205617445,
      "lon": 5.9326171875,
      "observed_on": "2026-02-20",
      "time": "14:56",
      "location_name": "Eys",
      "source": "waarneming_nl",
      "category": "bird",
      "rarity": 2,
      "rarity_label": "vrij_algemeen",
      "photo_url": "",
      "permalink": "https://waarneming.nl/observation/386372738/",
      "count": 20,
      "distance_km": 9.06
    },
    {
      "id": "wn_386404924",
      "species": "Steenuil",
      "scientific_name": "Athene noctua",
      "lat": 50.80633544921875,
      "lon": 5.805020332336426,
      "observed_on": "2026-02-20",
      "time": "18:29",
      "location_name": "Margraten - Bruisterbosch",
      "source": "waarneming_nl",
      "category": "bird",
      "rarity": 2,
      "rarity_label": "vrij_algemeen",
      "photo_url": "",
      "permalink": "https://waarneming.nl/observation/386404924/",
      "count": 1,
      "distance_km": 9.68
    },
    {
      "id": "wn_386380446",
      "species": "Rode Wouw",
      "scientific_name": "Milvus milvus",
      "lat": 50.842987060546875,
      "lon": 5.892653942108154,
      "observed_on": "2026-02-20",
      "time": "16:17",
      "location_name": "Ransdaal - Fromberg",
      "source": "waarneming_nl",
      "category": "bird",
      "rarity": 2,
      "rarity_label": "vrij_algemeen",
      "photo_url": "https://waarneming.nl/media/photo/144212127.jpg",
      "permalink": "https://waarneming.nl/observation/386380446/",
      "count": 1,
      "distance_km": 10.41
    },
    {
      "id": "wn_386383640",
      "species": "Kraanvogel",
      "scientific_name": "Grus grus",
      "lat": 50.85218811035156,
      "lon": 5.951093673706055,
      "observed_on": "2026-02-20",
      "time": "16:45",
      "location_name": "Ubachsberg",
      "source": "waarneming_nl",
      "category": "bird",
      "rarity": 2,
      "rarity_label": "vrij_algemeen",
      "photo_url": "",
      "permalink": "https://waarneming.nl/observation/386383640/",
      "count": 4,
      "distance_km": 11.72
    },
    {
      "id": "wn_386383079",
      "species": "Kraanvogel",
      "scientific_name": "Grus grus",
      "lat": 50.85218811035156,
      "lon": 5.951093673706055,
      "observed_on": "2026-02-20",
      "time": "16:45",
      "location_name": "Ubachsberg",
      "source": "waarneming_nl",
      "category": "bird",
      "rarity": 2,
      "rarity_label": "vrij_algemeen",
      "photo_url": "",
      "permalink": "https://waarneming.nl/observation/386383079/",
      "count": 4,
      "distance_km": 11.72
    },
    {
      "id": "wn_386363157",
      "species": "Houtsnip",
      "scientific_name": "Scolopax rusticola",
      "lat": 50.8405849947988,
      "lon": 5.771771889589737,
      "observed_on": "2026-02-20",
      "time": "11:20",
      "location_name": "'t Rooth - Groeve",
      "source": "waarneming_nl",
      "category": "bird",
      "rarity": 2,
      "rarity_label": "vrij_algemeen",
      "photo_url": "",
      "permalink": "https://waarneming.nl/observation/386363157/",
      "count": 1,
      "distance_km": 13.99
    },
    {
      "id": "wn_386383066",
      "species": "Wild Zwijn",
      "scientific_name": "Sus scrofa",
      "lat": 50.81989684525275,
      "lon": 5.743049383163452,
      "observed_on": "2026-02-20",
      "time": "14:23",
      "location_name": "Gronsveld - boomgaarden",
      "source": "waarneming_nl",
      "category": "mammal",
      "rarity": 2,
      "rarity_label": "vrij_algemeen",
      "photo_url": "https://waarneming.nl/media/photo/144210999.jpg",
      "permalink": "https://waarneming.nl/observation/386383066/",
      "count": 1,
      "distance_km": 14.08
    },
    {
      "id": "wn_386397846",
      "species": "Das",
      "scientific_name": "Meles meles",
      "lat": 50.820967765048,
      "lon": 5.741869211196899,
      "observed_on": "2026-02-20",
      "time": "14:31",
      "location_name": "Gronsveld - boomgaarden",
      "source": "waarneming_nl",
      "category": "mammal",
      "rarity": 2,
      "rarity_label": "vrij_algemeen",
      "photo_url": "https://waarneming.nl/media/photo/144218183.jpg",
      "permalink": "https://waarneming.nl/observation/386397846/",
      "count": 1,
      "distance_km": 14.21
    },
    {
      "id": "wn_386397876",
      "species": "Das",
      "scientific_name": "Meles meles",
      "lat": 50.82105047648279,
      "lon": 5.741423964500427,
      "observed_on": "2026-02-20",
      "time": "14:31",
      "location_name": "Heer - Hamsterreservaat e.o. ",
      "source": "waarneming_nl",
      "category": "mammal",
      "rarity": 2,
      "rarity_label": "vrij_algemeen",
      "photo_url": "https://waarneming.nl/media/photo/144218191.jpg",
      "permalink": "https://waarneming.nl/observation/386397876/",
      "count": 1,
      "distance_km": 14.24
    },
    {
      "id": "wn_386397937",
      "species": "Das",
      "scientific_name": "Meles meles",
      "lat": 50.821280923958504,
      "lon": 5.740780234336853,
      "observed_on": "2026-02-20",
      "time": "14:36",
      "location_name": "Heer - Hamsterreservaat e.o. ",
      "source": "waarneming_nl",
      "category": "mammal",
      "rarity": 2,
      "rarity_label": "vrij_algemeen",
      "photo_url": "https://waarneming.nl/media/photo/144218217.jpg",
      "permalink": "https://waarneming.nl/observation/386397937/",
      "count": 1,
      "distance_km": 14.29
    },
    {
      "id": "wn_386392699",
      "species": "Kraanvogel",
      "scientific_name": "Grus grus",
      "lat": 50.87115417409504,
      "lon": 5.978794097900391,
      "observed_on": "2026-02-20",
      "time": "17:36",
      "location_name": "Heerlen - Douveweien",
      "source": "waarneming_nl",
      "category": "bird",
      "rarity": 2,
      "rarity_label": "vrij_algemeen",
      "photo_url": "https://waarneming.nl/media/photo/144215851.jpg",
      "permalink": "https://waarneming.nl/observation/386392699/",
      "count": 90,
      "distance_km": 14.31
    },
    {
      "id": "wn_386385777",
      "species": "Kraanvogel",
      "scientific_name": "Grus grus",
      "lat": 50.804981653817734,
      "lon": 5.72417873194195,
      "observed_on": "2026-02-20",
      "time": "17:25",
      "location_name": "A2 - Gronsveld",
      "source": "waarneming_nl",
      "category": "bird",
      "rarity": 2,
      "rarity_label": "vrij_algemeen",
      "photo_url": "",
      "permalink": "https://waarneming.nl/observation/386385777/",
      "count": 30,
      "distance_km": 14.43
    },
    {
      "id": "wn_386363152",
      "species": "Houtsnip",
      "scientific_name": "Scolopax rusticola",
      "lat": 50.8458620373753,
      "lon": 5.768335233436679,
      "observed_on": "2026-02-20",
      "time": "09:36",
      "location_name": "Bemelen - Bemelerberg",
      "source": "waarneming_nl",
      "category": "bird",
      "rarity": 2,
      "rarity_label": "vrij_algemeen",
      "photo_url": "",
      "permalink": "https://waarneming.nl/observation/386363152/",
      "count": 1,
      "distance_km": 14.59
    },
    {
      "id": "wn_386363159",
      "species": "Wild Zwijn",
      "scientific_name": "Sus scrofa",
      "lat": 50.84618835813789,
      "lon": 5.765080093845299,
      "observed_on": "2026-02-20",
      "time": "11:44",
      "location_name": "Bemelen",
      "source": "waarneming_nl",
      "category": "mammal",
      "rarity": 2,
      "rarity_label": "vrij_algemeen",
      "photo_url": "",
      "permalink": "https://waarneming.nl/observation/386363159/",
      "count": 3,
      "distance_km": 14.77
    }
  ]
}