{
  "lat": 50.93,
  "lon": 6.21,
  "fetched_at": "2026-02-21T06:33:09.725001",
  "observation_count": 22,
  "observations": [
    {
      "id": "wn_386026416",
      "species": "Grote Zaagbek",
      "scientific_name": "Mergus merganser",
      "lat": 50.88077509702547,
      "lon": 6.052683591842651,
      "observed_on": "2026-02-14",
      "time": "15:08",
      "location_name": "Kerkrade - Cranenweyer",
      "source": "waarneming_nl",
      "category": "bird",
      "rarity": 2,
      "rarity_label": "vrij_algemeen",
      "photo_url": "https://waarneming.nl/media/photo/144044938.jpg",
      "permalink": "https://waarneming.nl/observation/386026416/",
      "count": 2,
      "distance_km": 12.31
    },
    {
      "id": "wn_386008143",
      "species": "Europese Rode Eekhoorn",
      "scientific_name": "Sciurus vulgaris",
      "lat": 50.8696488,
      "lon": 6.0270671,
      "observed_on": "2026-02-14",
      "time": "14:21",
      "location_name": "Kerkrade - Terwinselen",
      "source": "waarneming_nl",
      "category": "mammal",
      "rarity": 2,
      "rarity_label": "vrij_algemeen",
      "photo_url": "https://waarneming.nl/media/photo/144036843.jpg",
      "permalink": "https://waarneming.nl/observation/386008143/",
      "count": 1,
      "distance_km": 14.48
    },
    {
      "id": "wn_386127966",
      "species": "Grote Zaagbek",
      "scientific_name": "Mergus merganser",
      "lat": 50.884566088525325,
      "lon": 6.052844524383545,
      "observed_on": "2026-02-15",
      "time": "15:01",
      "location_name": "Kerkrade - Cranenweyer",
      "source": "waarneming_nl",
      "category": "bird",
      "rarity": 2,
      "rarity_label": "vrij_algemeen",
      "photo_url": "https://waarneming.nl/media/photo/144088667.jpg",
      "permalink": "https://waarneming.nl/observation/386127966/",
      "count": 2,
      "distance_km": 12.12
    },
    {
      "id": "wn_386257687",
      "species": "Rode Wouw",
      "scientific_name": "Milvus milvus",
      "lat": 50.90296405438591,
      "lon": 6.038985030455251,
      "observed_on": "2026-02-18",
      "time": "10:30",
      "location_name": "Landgraaf - Centrum / Nieuwenhagen",
      "source": "waarneming_nl",
      "category": "bird",
      "rarity": 2,
      "rarity_label": "vrij_algemeen",
      "photo_url": "",
      "permalink": "https://waarneming.nl/observation/386257687/",
      "count": 1,
      "distance_km": 12.36
    },
    {
      "id": "wn_386389149",
      "species": "Kraanvogel",
      "scientific_name": "Grus grus",
      "lat": 50.88039016723633,
      "lon": 6.08315896987915,
      "observed_on": "2026-02-20",
      "time": "14:56",
      "location_name": "Kerkrade - Wormdal - Haanrade - Zuid",
      "source": "waarneming_nl",
      "category": "bird",
      "rarity": 2,
      "rarity_label": "vrij_algemeen",
      "photo_url": "",
      "permalink": "https://waarneming.nl/observation/386389149/",
      "count": 40,
      "distance_km": 10.47
    },
    {
      "id": "wn_386372721",
      "species": "Kraanvogel",
      "scientific_name": "Grus grus",
      "lat": 50.88039016723633,
      "lon": 6.08315896987915,
      "observed_on": "2026-02-20",
      "time": "14:56",
      "location_name": "Kerkrade - Wormdal - Haanrade - Zuid",
      "source": "waarneming_nl",
      "category": "bird",
      "rarity": 2,
      "rarity_label": "vrij_algemeen",
      "photo_url": "",
      "permalink": "https://waarneming.nl/observation/386372721/",
      "count": 40,
      "distance_km": 10.47
    },
    {
      "id": "wn_386383704",
      "species": "Raaf",
      "scientific_name": "Corvus corax",
      "lat": 50.880340576171875,
      "lon": 6.082927227020264,
      "observed_on": "2026-02-20",
      "time": "11:25",
      "location_name": "Kerkrade - Wormdal - Haanrade - Zuid",
      "source": "waarneming_nl",
      "category": "bird",
      "rarity": 2,
      "rarity_label": "vrij_algemeen",
      "photo_url": "",
      "permalink": "https://waarneming.nl/observation/386383704/",
      "count": 1,
      "distance_km": 10.48
    },
    {
      "id": "wn_386383219",
      "species": "Raaf",
      "scientific_name": "Corvus corax",
      "lat": 50.880340576171875,
      "lon": 6.082927227020264,
      "observed_on": "2026-02-20",
      "time": "11:25",
      "location_name": "Kerkrade - Wormdal - Haanrade - Zuid",
      "source": "waarneming_nl",
      "category": "bird",
      "rarity": 2,
      "rarity_label": "vrij_algemeen",
      "photo_url": "",
      "permalink": "https://waarneming.nl/observation/386383219/",
      "count": 1,
      "distance_km": 10.48
    },
    {
      "id": "wn_386357938",
      "species": "Raaf",
      "scientific_name": "Corvus corax",
      "lat": 50.880332946777344,
      "lon": 6.082906723022461,
      "observed_on": "2026-02-20",
      "time": "11:26",
      "location_name": "Kerkrade - Wormdal - Haanrade - Zuid",
      "source": "waarneming_nl",
      "category": "bird",
      "rarity": 2,
      "rarity_label": "vrij_algemeen",
      "photo_url": "",
      "permalink": "https://waarneming.nl/observation/386357938/",
      "count": 1,
      "distance_km": 10.48
    },
    {
      "id": "wn_386398839",
      "species": "Raaf",
      "scientific_name": "Corvus corax",
      "lat": 50.88056182861328,
      "lon": 6.0825514793396,
      "observed_on": "2026-02-20",
      "time": "11:26",
      "location_name": "Kerkrade - Wormdal - Haanrade - Zuid",
      "source": "waarneming_nl",
      "category": "bird",
      "rarity": 2,
      "rarity_label": "vrij_algemeen",
      "photo_url": "",
      "permalink": "https://waarneming.nl/observation/386398839/",
      "count": 1,
      "distance_km": 10.49
    },
    {
      "id": "wn_386398845",
      "species": "Appelvink",
      "scientific_name": "Coccothraustes coccothraustes",
      "lat": 50.882118225097656,
      "lon": 6.080603122711182,
      "observed_on": "2026-02-20",
      "time": "11:16",
      "location_name": "Kerkrade - Wormdal - Haanrade",
      "source": "waarneming_nl",
      "category": "bird",
      "rarity": 2,
      "rarity_label": "vrij_algemeen",
      "photo_url": "",
      "permalink": "https://waarneming.nl/observation/386398845/",
      "count": 2,
      "distance_km": 10.52
    },
    {
      "id": "wn_386357943",
      "species": "Appelvink",
      "scientific_name": "Coccothraustes coccothraustes",
      "lat": 50.882137298583984,
      "lon": 6.080523490905762,
      "observed_on": "2026-02-20",
      "time": "11:16",
      "location_name": "Kerkrade - Wormdal - Haanrade",
      "source": "waarneming_nl",
      "category": "bird",
      "rarity": 2,
      "rarity_label": "vrij_algemeen",
      "photo_url": "",
      "permalink": "https://waarneming.nl/observation/386357943/",
      "count": 1,
      "distance_km": 10.52
    },
    {
      "id": "wn_386383712",
      "species": "Appelvink",
      "scientific_name": "Coccothraustes coccothraustes",
      "lat": 50.882118225097656,
      "lon": 6.080511093139648,
      "observed_on": "2026-02-20",
      "time": "11:16",
      "location_name": "Kerkrade - Wormdal - Haanrade",
      "source": "waarneming_nl",
      "category": "bird",
      "rarity": 2,
      "rarity_label": "vrij_algemeen",
      "photo_url": "",
      "permalink": "https://waarneming.nl/observation/386383712/",
      "count": 4,
      "distance_km": 10.53
    },
    {
      "id": "wn_386383229",
      "species": "Appelvink",
      "scientific_name": "Coccothraustes coccothraustes",
      "lat": 50.882118225097656,
      "lon": 6.080511093139648,
      "observed_on": "2026-02-20",
      "time": "11:16",
      "location_name": "Kerkrade - Wormdal - Haanrade",
      "source": "waarneming_nl",
      "category": "bird",
      "rarity": 2,
      "rarity_label": "vrij_algemeen",
      "photo_url": "",
      "permalink": "https://waarneming.nl/observation/386383229/",
      "count": 4,
      "distance_km": 10.53
    },
    {
      "id": "wn_386398848",
      "species": "Houtsnip",
      "scientific_name": "Scolopax rusticola",
      "lat": 50.8826789855957,
      "lon": 6.079162120819092,
      "observed_on": "2026-02-20",
      "time": "10:54",
      "location_name": "Kerkrade - Wormdal - Haanrade",
      "source": "waarneming_nl",
      "category": "bird",
      "rarity": 2,
      "rarity_label": "vrij_algemeen",
      "photo_url": "",
      "permalink": "https://waarneming.nl/observation/386398848/",
      "count": 1,
      "distance_km": 10.58
    },
    {
      "id": "wn_386357966",
      "species": "IJsvogel",
      "scientific_name": "Alcedo atthis",
      "lat": 50.882659912109375,
      "lon": 6.079169273376465,
      "observed_on": "2026-02-20",
      "time": "10:48",
      "location_name": "Kerkrade - Wormdal - Haanrade",
      "source": "waarneming_nl",
      "category": "bird",
      "rarity": 2,
      "rarity_label": "vrij_algemeen",
      "photo_url": "",
      "permalink": "https://waarneming.nl/observation/386357966/",
      "count": 1,
      "distance_km": 10.58
    },
    {
      "id": "wn_386357892",
      "species": "Houtsnip",
      "scientific_name": "Scolopax rusticola",
      "lat": 50.882659912109375,
      "lon": 6.079188346862793,
      "observed_on": "2026-02-20",
      "time": "10:50",
      "location_name": "Kerkrade - Wormdal - Haanrade",
      "source": "waarneming_nl",
      "category": "bird",
      "rarity": 2,
      "rarity_label": "vrij_algemeen",
      "photo_url": "",
      "permalink": "https://waarneming.nl/observation/386357892/",
      "count": 1,
      "distance_km": 10.58
    },
    {
      "id": "wn_386357975",
      "species": "Europese Rode Eekhoorn",
      "scientific_name": "Sciurus vulgaris",
      "lat": 50.88032998397227,
      "lon": 6.064976826310158,
      "observed_on": "2026-02-20",
      "time": "09:29",
      "location_name": "Kerkrade - Haanrade",
      "source": "waarneming_nl",
      "category": "mammal",
      "rarity": 2,
      "rarity_label": "vrij_algemeen",
      "photo_url": "",
      "permalink": "https://waarneming.nl/observation/386357975/",
      "count": 1,
      "distance_km": 11.57
    },
    {
      "id": "wn_386370454",
      "species": "Kraanvogel",
      "scientific_name": "Grus grus",
      "lat": 50.88433214612964,
      "lon": 6.060367114841938,
      "observed_on": "2026-02-20",
      "time": "13:10",
      "location_name": "Kerkrade - Eygelshoven",
      "source": "waarneming_nl",
      "category": "bird",
      "rarity": 2,
      "rarity_label": "vrij_algemeen",
      "photo_url": "",
      "permalink": "https://waarneming.nl/observation/386370454/",
      "count": 80,
      "distance_km": 11.66
    },
    {
      "id": "wn_386374528",
      "species": "Kraanvogel",
      "scientific_name": "Grus grus",
      "lat": 50.898059079295884,
      "lon": 6.051278114318848,
      "observed_on": "2026-02-20",
      "time": "14:20",
      "location_name": "Kerkrade - Eygelshoven",
      "source": "waarneming_nl",
      "category": "bird",
      "rarity": 2,
      "rarity_label": "vrij_algemeen",
      "photo_url": "",
      "permalink": "https://waarneming.nl/observation/386374528/",
      "count": 40,
      "distance_km": 11.68
    },
    {
      "id": "wn_386401941",
      "species": "Kleine Bonte Specht",
      "scientific_name": "Dryobates minor",
      "lat": 50.87665052601896,
      "lon": 6.054104156792164,
      "observed_on": "2026-02-20",
      "time": "22:23",
      "location_name": "Kerkrade - Cranenweyer",
      "source": "waarneming_nl",
      "category": "bird",
      "rarity": 2,
      "rarity_label": "vrij_algemeen",
      "photo_url": "",
      "permalink": "https://waarneming.nl/observation/386401941/",
      "count": 1,
      "distance_km": 12.44
    },
    {
      "id": "wn_386355002",
      "species": "Kraanvogel",
      "scientific_name": "Grus grus",
      "lat": 50.869483947753906,
      "lon": 6.025542259216309,
      "observed_on": "2026-02-20",
      "time": "11:01",
      "location_name": "Kerkrade - Terwinselen",
      "source": "waarneming_nl",
      "category": "bird",
      "rarity": 2,
      "rarity_label": "vrij_algemeen",
      "photo_url": "",
      "permalink": "https://waarneming.nl/observation/386355002/",
      "count": 4,
      "distance_km": 14.58
    }
  ]
}